{
  "name": "Amanda Clark",
  "age": 29,
  "address": {
    "street": "Bogwar Square",
    "city": "Jubadi",
    "state": "OH",
    "zip": "17859"
  },
  "contact": {
    "phone": "(708) 946-1108",
    "servicePhone": "800911129"
  },
  "birthday": "2003-04-01T17:55:53.331Z",
  "ip": "130.175.110.99",
  "foo": "bar",
  "profile": {
    "about": "Me je tujfeb tic hawok ipavig jer huh eckugoh cuzjaw lesevupe jip femta gelvekzoc ha. Puh kekechi vum lujiti cozazli wiljopoza li kikke ivce pelso pel uhizewo origo vufwucci kin. Nogveju apposaj ifekununi nagta loenegas bot vocramdo hof hoc kamcu wi emmuwil. Pegci nine tagdowu ramo zu pit ihvo boh wuv nora dajboam ijoso wimevo ubsela wos zeban cib harevzor. Mubikuv za duk gira covvurso rutcu ruw jumsi jiwvukow se nojjoz ruf kaepzu wurkagvus wanesbu te. Wiz voh mob nuuvasu haju sajubgil fec ima fa leh kowose wah bes tevin bohnamu gukictu.",
    "bio": "Fo ocu zev semilri usben hovor nanvom fiz fak orobo bollig ci jugoj. Ta lev doleszi cinij fuz it zalis fib nefcu ofa nam ripe kokgirop ofu awewelfih nikiwfe. Ne adco hu aspe dodda ludwal bomu taok dam laji wemvofti okcoacu lal acbiti su subsehlo."
  },
  "apiKey": "cd2348e323f9253c0e14ab0e03cd7c69231d8d03fd0242fbf63057da3fdac135",
  "currency": {
    "code": "XCD",
    "name": "East Caribbean Dollar"
  }
}