{
  "name": "Harriett Roy",
  "age": 37,
  "address": {
    "street": "Hawpe Manor",
    "city": "Iglifmot",
    "state": "WA",
    "zip": "55644"
  },
  "contact": {
    "phone": "(471) 773-4591",
    "servicePhone": "800718916"
  },
  "birthday": "1999-09-28T11:16:29.176Z",
  "ip": "66.64.127.133",
  "foo": "bar",
  "profile": {
    "about": "Nimdo jobim sowiw sajrampas zirogrun rupok isicec belzur ijfig onongu maveg pohamu je ewehowdi neamce di ertav oc. Dorpu rahjoz bog ke patka zafi aloki ne gevuc dizpigzuk siwbe suszelto cifora lasdis vetegapih mizikaw gacilaw ci. Migewewi negujje herkuugu gu risfew saow kecuge nu wefoz sezcamik di ehifeve hackem tare upruj. Matina ow diweh min viwnuav hedkoc mog bi polip tabi cedhez ifaimwa. Zif lofjoku jare ugowir zorwo owzuid awri ujba basfiztag lamzop vos pebiigu upbum apukow uwojbak piv. Gidol momfuzto ihcem ida pa dab cev owiak kakhup feptom koz nedijuz wimanaf weornom sip litbo. Pif vefej leljule ritip wutitsig jigfi zedco al wibta ovusawa mo se lem leze maziddit.",
    "bio": "Gud lodedlut be tuw toovgaf zihmu zenwop wahwih azfugak zoeb bebweej lawvaspuk nepmaku wu noppaci fopecgas vorizik naijpu. Abi dar dop vujomih if ajiebopo idevaswa saw ucdelkuv sereka re sujuz rez. Lewofu manfi joz lo ez tubab vaniz nepvuhu ebgokah uvodkad re binec fazu gibaf. Ne fip neshab wab fosranib sucnid savef fipwoh dasvohof zavhok vagowodog be. Suwdapu dehaoga midovzi rarwoc ziwnafton mur wupiso bucoc motob zedkap kunrakdul tov zofbef. Jowazguv pa ar ju gufalod potjaj daolo ecbivret mirkolvu vazlunor asonu am tot ku ferasir ja gubir. Dat mumdu ekola utwiv ta rumvumij zac ne ruz wekleziv hecid tatdehcu hovawja uveza wef zur lic."
  },
  "apiKey": "581040fcc0d9215219f98c18095902534549d4a4dc34e499d4579b2e8f0d6100",
  "currency": {
    "code": "GBP",
    "name": "United Kingdom Pound"
  }
}