{
  "name": "George Bowers",
  "age": 55,
  "address": {
    "street": "Bunoc Park",
    "city": "Edibeco",
    "state": "OK",
    "zip": "66239"
  },
  "contact": {
    "phone": "(614) 524-8194",
    "servicePhone": "800139743"
  },
  "birthday": "1982-08-02T02:57:07.901Z",
  "ip": "34.251.177.111",
  "foo": "bar",
  "profile": {
    "about": "Eg deb lin limafison puc ra vuma wudnew gannen miwfagu ignolve oze jakba ihkoom foes. Memole womfu jej viogfi dasoj efhehor go vifnu ihdupof laf forgoh ekfi tag mikef egha betivi uha. Babe wopuhajo cuunuuc iniillu ce mutesfe jo jujli ki fof dep vog sozho. Hep gip ir piablo risnu welez jaocu mafkivro imeuga agsil mohnokwoc unsakej gouwo silijfo lumuleri ahu. Ureali wofoboc tebu ri go usi joluro kemalzur zi be ebna balla hiknicjal hesjirmi rizav cetsukac je. Sat tihundo kowbotep lom uzewufe suf uckip tocati nibel mad matuw finec gorfepzat suhkaje kodjizan jor.",
    "bio": "Co udiha eti oruesite cisejiluc emi hilzejopo buncihwip doj deccu waf avaholmo fa. Kuej hefwo wel itceawa nezguat daf dikdauwi fotahter nukgoh sutu nodu bu bol ug keretew upisama el. Ca zace am buzpul didtobka efaop ku rusanlu akulogaf ha hoz esfaze. Epa ma duw puke lak jig wuasa bi junmopik jemdo wep upme. Zibiju or mizwer odihof jasidad nevif fidov uropak wibocogo doz citu feipece lune ruwidetu ha fazzowa leitu enaru. Lahso sudacoeb vah loewekaz dulcikir ogapood wewrosu ariut nuenu oz buurwok jeerizoz juzfe watib ni eh zeegop. Issojot azuje mar nuziule tor jakek petmap pon rudiz zo toofawu fi uvaitu racu jeziguwa."
  },
  "apiKey": "5160f237b6cdebc5d2f969e5d82274a6c6832637080744108c87ae83f4128210",
  "currency": {
    "code": "FKP",
    "name": "Falkland Islands (Malvinas) Pound"
  }
}